[
  {
    "name": "items",
    "type": "array",
    "required": true,
    "description": "",
    "params": [
      {
        "name": "imageSrc",
        "type": "string",
        "required": false,
        "description": ""
      },
      {
        "name": "imageAlt",
        "type": "string",
        "required": false,
        "description": ""
      },
      {
        "name": "imageWidth",
        "type": "number",
        "required": false,
        "description": ""
      },
      {
        "name": "imageHeight",
        "type": "number",
        "required": false,
        "description": ""
      },
      {
        "name": "collection",
        "type": "string",
        "required": true,
        "description": ""
      },
      {
        "name": "title",
        "type": "string",
        "required": true,
        "description": ""
      },
      {
        "name": "href",
        "type": "string",
        "required": true,
        "description": ""
      },
      {
        "name": "date",
        "type": "string",
        "required": false,
        "description": ""
      }
    ]
  },
  {
    "name": "classes",
    "type": "string",
    "required": false,
    "description": "Classes to add to the filters."
  },
  {
    "name": "attributes",
    "type": "object",
    "required": false,
    "description": "HTML attributes (for example data attributes) to add to the filters."
  }
]
